{
    "pipeline_function": "silver.edsm_silver_load",
    "src_table_name": "edsm.bronze.bodies7days",
    "dst_table_name": "edsm.silver.bodies7days",
    "build_history": "true",
    "composite_key": [
        "id"
    ],
    "business_key": [
        "materials",
        "updateTime"
    ],
    "data_type_map": {
        "date": "timestamp"
    },
    "readStreamOptions": {},
    "writeStreamOptions": {
        "mergeSchema": "false",
        "checkpointLocation": "/Volumes/edsm/silver/utility/bodies7days/_checkpoints/",
        "delta.columnMapping.mode": "name"
    }
}